MANIFEST.in
README.rst
setup.py
src/django_wiretap.egg-info/PKG-INFO
src/django_wiretap.egg-info/SOURCES.txt
src/django_wiretap.egg-info/dependency_links.txt
src/django_wiretap.egg-info/requires.txt
src/django_wiretap.egg-info/top_level.txt
src/wiretap/__init__.py
src/wiretap/admin.py
src/wiretap/middleware.py
src/wiretap/models.py
src/wiretap/signals.py
src/wiretap/tests.py