Metadata-Version: 1.1
Name: django-wiretap
Version: 0.1.2
Summary: https://github.com/nathforge/django-wiretap
Home-page: https://github.com/nathforge/django-wiretap
Author: Nathan Reynolds
Author-email: email@nreynolds.co.uk
License: UNKNOWN
Platform: UNKNOWN
Classifier: Programming Language :: Python
Classifier: Programming Language :: Python :: 3
